jancode/__init__.py
jancode/characters.py
jancode/check_digit.py
jancode/convert.py
jancode/create_svg.py
jancode/main.py
jancode/property.py
jancode-1.0.0.dist-info/METADATA
jancode-1.0.0.dist-info/WHEEL
jancode-1.0.0.dist-info/top_level.txt
jancode-1.0.0.dist-info/RECORD
