Metadata-Version: 2.1
Name: jancode
Version: 1.0.0
Summary: Generate JANcode
Home-page: https://github.com/yashikota/jancode
Author: kota
Author-email: 52403688+yashikota@users.noreply.github.com
Maintainer: kota
Maintainer-email: 52403688+yashikota@users.noreply.github.com
License: MIT
Download-URL: https://github.com/yashikota/jancode
Keywords: jancode
Platform: UNKNOWN
Classifier: License :: OSI Approved :: MIT License
Classifier: Programming Language :: Python :: 3.6
